{
    "translation": {
        "home": "ホーム",
        "faucet": "フォーセット",
        "getFreeSupra": "無料Supraを獲得",
        "disconnect": "接続を切る",
        "connectWallet": "ウォレットを接続",
        "welcome": "SpikeyFunへようこそ！",
        "verifyingAccount": "アカウントを確認中...",
        "accountReady": "アカウントの準備ができました！トークンを請求してください。",
        "registrationFailed": "登録に失敗しました。",
        "error": "エラー: ",
        "hideInformation": "情報を隠す",
        "needToKnowMore": "もっと詳しく知りたいですか？",
        "firstStep": "無料トークンを受け取るための最初のステップ。",
        "yourCurrentBalance": "現在の残高",
        "claiming": "請求中...",
        "getSupra": "{amount} SUPRAを獲得",
        "successBalanceUpdating": "成功！残高を更新中です。",
        "lastTx": "最終トランザクション: ",
        "welcomeToSupraFaucet": "Supra Faucetへようこそ",
        "getSmallAmount": "ネットワークを試すために少量のSUPRAを入手しましょう—購入は不要です。",
        "whatIsSupra": "Supraとは？",
        "supraDescription": "Supraは、速度、わずかな手数料、開発者に優しい自動化に焦点を当てた次世代のレイヤー1ブロックチェーンです。SUPRAトークンは、リアルタイムオラクルやプログラム可能な自動化などのトランザクション、ガバナンス、スマート機能を強化し、アプリをより速く、ユーザーにとってよりシンプルにします。これは、チームが遅い確認や高コストに悩まされることなく、便利なアプリを出荷できるように構築されたブロックチェーンと考えてください。",
        "whySupraIsDifferent": "Supraが異なる理由",
        "ultraFast": "超高速＆低コスト：瞬時のファイナリティと最小限の手数料のために設計されています。",
        "realTimeData": "リアルタイムデータ：組み込みのオラクルがライブ情報をスマートコントラクトにもたらします。",
        "automationReady": "自動化対応：スケジュールされたタスクと信頼性の高いオンチェーンワークフローのためのネイティブツール。",
        "developerFriendly": "開発者に優しい：プロジェクトをより迅速に立ち上げるためのSDK、ブリッジ、統合。",
        "whatIsThisFaucetFor": "このフォーセットは何のためですか？",
        "faucetPurpose": "このフォーセットは、誰でもお金をかけずにネットワークを探索できるように少量のSUPRAを提供します。ウォレットやdAppを試す初心者、機能をテストする開発者、実践を通して学びたい好奇心旺盛なユーザーに最適です。",
        "howItWorks": "仕組み",
        "connectWalletStep": "互換性のあるウォレットを接続します（例：Starkey）。",
        "verifyStep": "確認 — 悪用を防ぐために迅速な自動チェックを実行します。",
        "claimStep": "請求 — ボタンを押して、数秒以内にオンチェーンでトークンを受け取ります。",
        "tip": "ヒント：1アドレスにつき1回の請求。問題が発生した場合は、ウォレットのネットワーク設定を確認するか、サポートにお問い合わせください。",
        "readyToTry": "Supraを試す準備はできましたか？ウォレットを接続して請求し、dAppsを探索したり、流動性を追加したり、独自のプロジェクトを構築したりしてください。バナーやモバイルビュー用の短いバージョンが必要な場合は、それも準備できます。",
        "freeSupraCoins": "Free Supracoins",
        "tokensAvailable": "フォーセットで利用可能なトークン",
        "loading": "読み込み中...",
        "notAvailable": "N/A",
        "copied": "コピーしました！",
        "copy": "コピー",
        "SuccessModal": {
            "title": "Transaction Successful!",
            "message": "Your transaction has been processed successfully.<br/>Transaction Hash: <link>{hash}</link>",
            "buttonText": "Awesome!"
        },
        "ErrorModal": {
            "title": "Transaction Failed",
            "buttonText": "Close"
        },
        "mainnetShort": "Mainnet",
        "testnetShort": "Testnet",
        "holdToSwitch": "Hold for {seconds}s to switch to {networkName}",
        "joinSupraCommunity": "Supraコミュニティに参加"
    },
    "wallets": {
      "connected": "Connected",
      "title": "Connect Wallet",
      "closeButtonLabel": "Close",
      "description": "Connect your wallet to continue"
    },
    "Footer": {
        "brandName": "Spikey Corp",
        "copyright": "© {year} Spikey Corp. All rights reserved.",
        "explore": "Explore",
        "community": "Join the Community",
        "whitepaper": "Whitepaper",
        "terms": "Terms of Service",
        "privacy": "Privacy Policy",
        "secretTooltip": "What's this?",
        "secretTooltip2": "Keep going...",
        "secretTooltip3": "One more time!"
    }
}